phroc/__init__.py
phroc/gui.py
phroc/meta.py
phroc/run.py
phroc/process/__init__.py
phroc/process/parameters.py
phroc/process/qc.py
phroc/process/read.py
phroc/process/read_raw.py
phroc/process/usd.py
phroc/process/write.py
phroc-0.3.dist-info/LICENSE
phroc-0.3.dist-info/METADATA
phroc-0.3.dist-info/WHEEL
phroc-0.3.dist-info/entry_points.txt
phroc-0.3.dist-info/top_level.txt
phroc-0.3.dist-info/RECORD
